ccaawscreds/__init__.py
ccaawscreds/credentials.py
ccaawscreds/iamuser.py
ccaawscreds/inifile.py
ccaawscreds/pwgen.py
ccaawscreds/wordlist.txt
ccaawscreds-0.5.6.dist-info/entry_points.txt
ccaawscreds-0.5.6.dist-info/WHEEL
ccaawscreds-0.5.6.dist-info/METADATA
ccaawscreds-0.5.6.dist-info/RECORD
