Metadata-Version: 2.1
Name: ccaawscreds
Version: 0.5.6
Summary: update AWS console PW, rotate Access Keys, generate random passwords.
Home-page: https://github.com/ccdale/ccaawscreds
License: GPL-3.0-or-later
Author: ccdale
Author-email: chris.charles.allison@gmail.com
Requires-Python: >=3.7,<4.0
Classifier: License :: OSI Approved :: GNU General Public License v3 or later (GPLv3+)
Classifier: Programming Language :: Python :: 3
Classifier: Programming Language :: Python :: 3.7
Classifier: Programming Language :: Python :: 3.8
Requires-Dist: boto3 (>=1.14.48,<2.0.0)
Requires-Dist: click (>=7.1.2,<8.0.0)
Project-URL: Repository, https://github.com/ccdale/ccaawscreds
